verilog/FA_nbit/FA_1bit.v
module FA(output rout, output z, input rin, input a, input b);
  assign 
    rout = (a && b) || (b&&rin) || (a&&rin);
  assign 
    z = (!a && !b && rin) || (!a && b && !rin) || (a && !b && !rin) || (a && b && rin);
endmodule

verilog/FA_nbit/FA_nbit.v
module FA_nbit(output rout, output [N-1:0] z, input rin, input [N-1:0] a, input [N-1:0] b);
  parameter N = 2; // inserisco un valore di default nel caso non sia stato passato il parmetro
  wire [N-1:0] rips; // il riporto dopo la somma cambia su FA1
  FA primo (rips[0], z[0], rin, a[0], b[0]);
  genvar i; // specifico che la i deve far parte di un for generativo
  generate // for generativo = significa che sto creando un numero parametrico di componenti
    for (i = 1; i<N-1; i=i+1) begin
      FA fa (rips[i], z[i], rips[i-1], a[i], b[i]);
    end
  endgenerate
  FA ultimo (rout, z[N-1], rips[N-2], a[N-1], b[N-1]);
endmodule

verilog/FA_nbit/main.v
module main;
  parameter N = 2; // inserisco un valore di default nel caso non sia stato passato il parmetro
  reg [N-1:0] a; // sintassi per dire che a è una tupla e a[0] è il bit più significativo
  reg [N-1:0] b;
  reg rin;

  wire rout;
  wire [N-1:0] z;

  integer i;
  integer nfor= N*3;
  FA_nbit adder (rout,z,rin,a,b);

  initial
    begin
      a=0;
      b=0;
      rin=0;

      $dumpfile("test_fa.vcd");
      $dumpvars;

      #1 $display("(a b rin) => (rout z)");

      for(i=0; i<(2**nfor); i+=1) // bisogna fare la potenza per calcolare tutte le possibili combinazioni di input
        begin
          #2 {a,b,rin}=i;
          #1 $display("(%b %b %b) => (%b %b)", a, b, rin, rout, z);
        end
      $finish;
    end 

endmodule

verilog/FA_nbit/test_fa.vcd
$date
	Sat Oct 19 10:01:48 2024
$end
$version
	Icarus Verilog
$end
$timescale
	1s
$end
$scope module main $end
$var wire 2 ! z [1:0] $end
$var wire 1 " rout $end
$var reg 2 # a [1:0] $end
$var reg 2 $ b [1:0] $end
$var reg 1 % rin $end
$var integer 32 & i [31:0] $end
$var integer 32 ' nfor [31:0] $end
$scope module adder $end
$var wire 2 ( a [1:0] $end
$var wire 2 ) b [1:0] $end
$var wire 1 % rin $end
$var wire 2 * z [1:0] $end
$var wire 1 " rout $end
$var wire 2 + rips [1:0] $end
$scope module primo $end
$var wire 1 , a $end
$var wire 1 - b $end
$var wire 1 % rin $end
$var wire 1 . rout $end
$var wire 1 / z $end
$upscope $end
$scope module ultimo $end
$var wire 1 0 a $end
$var wire 1 1 b $end
$var wire 1 2 rin $end
$var wire 1 " rout $end
$var wire 1 3 z $end
$upscope $end
$upscope $end
$upscope $end
$enddefinitions $end
#0
$dumpvars
03
02
01
00
0/
0.
0-
0,
bz0 +
b0 *
b0 )
b0 (
b110 '
bx &
0%
b0 $
b0 #
0"
b0 !
$end
#1
b0 &
#4
b1 &
#6
b1 !
b1 *
1/
1%
#7
b10 &
#9
b1 !
b1 *
1/
1-
b1 $
b1 )
0%
#10
b11 &
#12
13
12
b10 !
b10 *
0/
bz1 +
1.
1%
#13
b100 &
#15
13
0"
02
b10 !
b10 *
0/
bz0 +
0.
0-
11
b10 $
b10 )
0%
#16
b101 &
#18
b11 !
b11 *
1/
1%
#19
b110 &
#21
b11 !
b11 *
1/
1-
b11 $
b11 )
0%
#22
b111 &
#24
03
1"
12
b0 !
b0 *
0/
bz1 +
1.
1%
#25
b1000 &
#27
03
0"
02
b1 !
b1 *
1/
bz0 +
0.
1,
0-
01
b1 #
b1 (
b0 $
b0 )
0%
#28
b1001 &
#30
13
12
b10 !
b10 *
0/
bz1 +
1.
1%
#31
b1010 &
#33
13
12
b10 !
b10 *
0/
bz1 +
1.
1-
b1 $
b1 )
0%
#34
b1011 &
#36
b11 !
b11 *
1/
1%
#37
b1100 &
#39
13
02
bz0 +
0.
0"
b11 !
b11 *
1/
0-
11
b10 $
b10 )
0%
#40
b1101 &
#42
03
1"
12
b0 !
b0 *
0/
bz1 +
1.
1%
#43
b1110 &
#45
03
1"
12
b0 !
b0 *
0/
bz1 +
1.
1-
b11 $
b11 )
0%
#46
b1111 &
#48
b1 !
b1 *
1/
1%
#49
b10000 &
#51
13
0"
02
bz0 +
0.
b10 !
b10 *
0/
0,
10
0-
01
b10 #
b10 (
b0 $
b0 )
0%
#52
b10001 &
#54
b11 !
b11 *
1/
1%
#55
b10010 &
#57
b11 !
b11 *
1/
1-
b1 $
b1 )
0%
#58
b10011 &
#60
03
1"
12
b0 !
b0 *
0/
bz1 +
1.
1%
#61
b10100 &
#63
03
02
b0 !
b0 *
0/
bz0 +
0.
0-
11
b10 $
b10 )
0%
#64
b10101 &
#66
b1 !
b1 *
1/
1%
#67
b10110 &
#69
b1 !
b1 *
1/
1-
b11 $
b11 )
0%
#70
b10111 &
#72
13
12
b10 !
b10 *
0/
bz1 +
1.
1%
#73
b11000 &
#75
0"
13
02
b11 !
b11 *
1/
bz0 +
0.
1,
0-
01
b11 #
b11 (
b0 $
b0 )
0%
#76
b11001 &
#78
03
1"
12
b0 !
b0 *
0/
bz1 +
1.
1%
#79
b11010 &
#81
03
1"
12
b0 !
b0 *
0/
bz1 +
1.
1-
b1 $
b1 )
0%
#82
b11011 &
#84
b1 !
b1 *
1/
1%
#85
b11100 &
#87
02
bz0 +
0.
03
b1 !
b1 *
1/
0-
11
b10 $
b10 )
0%
#88
b11101 &
#90
13
12
b10 !
b10 *
0/
bz1 +
1.
1%
#91
b11110 &
#93
13
12
b10 !
b10 *
0/
bz1 +
1.
1-
b11 $
b11 )
0%
#94
b11111 &
#96
b11 !
b11 *
1/
1%
#97
b100000 &
#99
02
bz0 +
0.
03
0"
b0 !
b0 *
0/
0,
00
0-
01
b0 #
b0 (
b0 $
b0 )
0%
#100
b100001 &
#102
b1 !
b1 *
1/
1%
#103
b100010 &
#105
b1 !
b1 *
1/
1-
b1 $
b1 )
0%
#106
b100011 &
#108
13
12
b10 !
b10 *
0/
bz1 +
1.
1%
#109
b100100 &
#111
13
0"
02
b10 !
b10 *
0/
bz0 +
0.
0-
11
b10 $
b10 )
0%
#112
b100101 &
#114
b11 !
b11 *
1/
1%
#115
b100110 &
#117
b11 !
b11 *
1/
1-
b11 $
b11 )
0%
#118
b100111 &
#120
03
1"
12
b0 !
b0 *
0/
bz1 +
1.
1%
#121
b101000 &
#123
03
0"
02
b1 !
b1 *
1/
bz0 +
0.
1,
0-
01
b1 #
b1 (
b0 $
b0 )
0%
#124
b101001 &
#126
13
12
b10 !
b10 *
0/
bz1 +
1.
1%
#127
b101010 &
#129
13
12
b10 !
b10 *
0/
bz1 +
1.
1-
b1 $
b1 )
0%
#130
b101011 &
#132
b11 !
b11 *
1/
1%
#133
b101100 &
#135
13
02
bz0 +
0.
0"
b11 !
b11 *
1/
0-
11
b10 $
b10 )
0%
#136
b101101 &
#138
03
1"
12
b0 !
b0 *
0/
bz1 +
1.
1%
#139
b101110 &
#141
03
1"
12
b0 !
b0 *
0/
bz1 +
1.
1-
b11 $
b11 )
0%
#142
b101111 &
#144
b1 !
b1 *
1/
1%
#145
b110000 &
#147
13
0"
02
bz0 +
0.
b10 !
b10 *
0/
0,
10
0-
01
b10 #
b10 (
b0 $
b0 )
0%
#148
b110001 &
#150
b11 !
b11 *
1/
1%
#151
b110010 &
#153
b11 !
b11 *
1/
1-
b1 $
b1 )
0%
#154
b110011 &
#156
03
1"
12
b0 !
b0 *
0/
bz1 +
1.
1%
#157
b110100 &
#159
03
02
b0 !
b0 *
0/
bz0 +
0.
0-
11
b10 $
b10 )
0%
#160
b110101 &
#162
b1 !
b1 *
1/
1%
#163
b110110 &
#165
b1 !
b1 *
1/
1-
b11 $
b11 )
0%
#166
b110111 &
#168
13
12
b10 !
b10 *
0/
bz1 +
1.
1%
#169
b111000 &
#171
0"
13
02
b11 !
b11 *
1/
bz0 +
0.
1,
0-
01
b11 #
b11 (
b0 $
b0 )
0%
#172
b111001 &
#174
03
1"
12
b0 !
b0 *
0/
bz1 +
1.
1%
#175
b111010 &
#177
03
1"
12
b0 !
b0 *
0/
bz1 +
1.
1-
b1 $
b1 )
0%
#178
b111011 &
#180
b1 !
b1 *
1/
1%
#181
b111100 &
#183
02
bz0 +
0.
03
b1 !
b1 *
1/
0-
11
b10 $
b10 )
0%
#184
b111101 &
#186
13
12
b10 !
b10 *
0/
bz1 +
1.
1%
#187
b111110 &
#189
13
12
b10 !
b10 *
0/
bz1 +
1.
1-
b11 $
b11 )
0%
#190
b111111 &
#192
b11 !
b11 *
1/
1%
#193
b1000000 &
